{"MzQe7kkcGU8FrbvNVwA6Vg==":"cropped-about-me.png-96x96.png","9XXXc0fcjtDRNzumZMoBxg==":"about-me.jpg-1489x838.jpg","68b83o3/L0hv3JzgE/OXaQ==":"ozan.png-1024x1536.png","z/pVQhtGdeja4XsJuEOvxQ==":"bilbots.png-712x712.png","ttmJ32wus4HWlbTILYMYuA==":"img-20241221-154139-618.jpg-712x320.jpeg","dZ1sxsqpSUd3Df0+jqRFNw==":"97101058-0e17-4994-8ffd-e978a0ae6e9e.url-0001.jpg-712x1007.jpg","gKkdq1z5Mo892GNexIQZ/w==":"dsc-0519.jpg-1101x1650.jpeg","PH1+6CUmay2RC0Xbdk3Qfw==":"dsc-0519.jpg-518x776.jpeg","FWfaGJmtXy7r11k7YkdNpA==":"dsc-0503.jpg-518x776.jpeg","pSEhdUAq9HU6ZpaELRtLzg==":"dsc-0499.jpg-518x776.jpeg","5w26xwl8PG7ghqHXNfjTdg==":"dsc-0495.jpg-518x776.jpeg","MWsLyb4+a913EsZVl0rYqg==":"dsc-0502.jpg-518x776.jpeg","M5LEcQJqZk/xWQDtH3Eweg==":"img-20241011-142827-966.jpg-4480x2016.jpg","F8NGjunG+nl058fb/w6YGQ==":"img-20241011-142827-966.jpg-4480x2016.jpeg","0GO9o9LXyWE1/9zSn7esFw==":"img-20241221-123932-0.jpg-1920x1080.jpg","mvMCDpY35aelRQjm4GiY8Q==":"whatsapp-image-2025-04-07-at-19.53.19.jpeg-721x1600.jpeg","z+sEIPcOKm5RTyrzKAd1UA==":"whatsapp-image-2025-04-07-at-19.53.19.jpeg-1-721x1600.jpeg","vcQifB5ZD24enIysVE6YXA==":"whatsapp-image-2025-04-07-at-19.53.19.jpeg-137x304.jpeg","bs8UVAlaZh/ps9S1Kx430w==":"whatsapp-image-2025-04-07-at-19.53.19.jpeg-1-137x304.jpeg","LZV0L26GDtEYi/NX3xz25Q==":"whatsapp-image-2025-04-07-at-19.53.19.jpeg-2-721x1600.jpeg"}